setup.cfg
setup.py
BRData/__init__.py
BRData.egg-info/PKG-INFO
BRData.egg-info/SOURCES.txt
BRData.egg-info/dependency_links.txt
BRData.egg-info/not-zip-safe
BRData.egg-info/top_level.txt