Metadata-Version: 2.1
Name: BRData
Version: 1.0
Summary: Random data for debuging all
Home-page: UNKNOWN
Author-email: gorunovila82@gmail.com
License: UNKNOWN
Platform: UNKNOWN
